shabakhti/__init__.py
shabakhti/main.py
shabakhti-0.9.4.dist-info/METADATA
shabakhti-0.9.4.dist-info/WHEEL
shabakhti-0.9.4.dist-info/top_level.txt
shabakhti-0.9.4.dist-info/RECORD
