Metadata-Version: 2.1
Name: shabakhti
Version: 0.9.4
Summary: Weather package
Home-page: https://github.com/mohammadlegend
Author: Mohammad Mahdi Shabakhti
Classifier: Programming Language :: Python :: 3
Classifier: License :: OSI Approved :: MIT License
Classifier: Operating System :: OS Independent
Requires-Python: >=3.6
Requires-Dist: requests
Requires-Dist: pyttsx3
